<?xml version="1.0" encoding="utf-8"?>
<SiPolicy xmlns:xsi="http://www.w3.org/2001/XMLSchema-instance" xmlns:xsd="http://www.w3.org/2001/XMLSchema" PolicyType="Supplemental Policy" xmlns="urn:schemas-microsoft-com:sipolicy">
  <VersionEx>10.0.0.0</VersionEx>
  <PlatformID>{2E07F7E4-194C-4D20-B7C9-6F44A6C5A234}</PlatformID>
  <PolicyID>{B5C8D1E7-A920-4E0C-BD86-783BB59C145E}</PolicyID>
  <BasePolicyID>{E0ABDA1F-CCF0-468E-8855-3E0F08B02D6A}</BasePolicyID>
  <Rules>
    <Rule>
      <Option>Enabled:Unsigned System Integrity Policy</Option>
    </Rule>
    <Rule>
      <Option>Enabled:Inherit Default Policy</Option>
    </Rule>
  </Rules>
  <EKUs />
  <FileRules />
  <Signers>
    <Signer Name="Allow CN = Dell Inc issued by Entrust Extended Validation Code Signing CA - EVCS1" ID="ID_SIGNER_A_4">
      <CertRoot Type="TBS" Value="F0E2990F9A3F198BA4996F5608E378375E8EA62464FC51AF1C528213F6CD57D5" />
      <CertPublisher Value="Dell Inc" />
    </Signer>
    <Signer Name="Allow CN = Dell Inc issued by DigiCert SHA2 Assured ID Code Signing CA" ID="ID_SIGNER_A_5">
      <CertRoot Type="TBS" Value="E767799478F64A34B3F53FF3BB9057FE1768F4AB178041B0DCC0FF1E210CBA65" />
      <CertPublisher Value="Dell Inc" />
    </Signer>
    <Signer Name="Allow CN = Dell Inc issued by Entrust Extended Validation Code Signing CA - EVCS2" ID="ID_SIGNER_A_6">
      <CertRoot Type="TBS" Value="F3A88B3AF739B6D92E4EB0B0971747A7B742ECBD82A83F9C7706776A3DC8ECE0176B32B1225CAB1287B84B3598AF5EAFDFF55D86C288AF4168D3FAE76D286E99" />
      <CertPublisher Value="Dell Inc" />
    </Signer>
    <Signer Name="Allow CN = Dell Inc issued by Entrust Code Signing CA - OVCS2" ID="ID_SIGNER_A_7">
      <CertRoot Type="TBS" Value="2893F2A6FDB108AC57D597754078350C55CAA720A072BD7BA170C8414B6749ECB2F875D29C77BC7AB7BF43D30D78424246F83CF66918BB601CE234429ACF3F2C" />
      <CertPublisher Value="Dell Inc" />
    </Signer>
    <Signer Name="Allow CN = Dell Inc. issued by VeriSign Class 3 Code Signing 2004 CA" ID="ID_SIGNER_A_8">
      <CertRoot Type="TBS" Value="C7FC1727F5B75A6421A1F95C73BBDB23580C48E5" />
      <CertPublisher Value="Dell Inc." />
    </Signer>
    <Signer Name="Allow CN = Dell Inc. issued by VeriSign Class 3 Code Signing 2010 CA" ID="ID_SIGNER_A_9">
      <CertRoot Type="TBS" Value="4678C6E4A8787A8E6ED2BCE8792B122F6C08AFD8" />
      <CertPublisher Value="Dell Inc." />
    </Signer>
    <Signer Name="Allow CN = Dell Inc. issued by Symantec Class 3 SHA256 Code Signing CA" ID="ID_SIGNER_A_10">
      <CertRoot Type="TBS" Value="A08E79C386083D875014C409C13D144E0A24386132980DF11FF59737C8489EB1" />
      <CertPublisher Value="Dell Inc." />
    </Signer>
    <Signer Name="Allow CN = Dell Inc. issued by Entrust Code Signing CA - OVCS2" ID="ID_SIGNER_A_11">
      <CertRoot Type="TBS" Value="2893F2A6FDB108AC57D597754078350C55CAA720A072BD7BA170C8414B6749ECB2F875D29C77BC7AB7BF43D30D78424246F83CF66918BB601CE234429ACF3F2C" />
      <CertPublisher Value="Dell Inc." />
    </Signer>
    <Signer Name="Allow CN = Dell Technologies Inc. issued by Entrust Extended Validation Code Signing CA - EVCS2" ID="ID_SIGNER_A_12">
      <CertRoot Type="TBS" Value="F3A88B3AF739B6D92E4EB0B0971747A7B742ECBD82A83F9C7706776A3DC8ECE0176B32B1225CAB1287B84B3598AF5EAFDFF55D86C288AF4168D3FAE76D286E99" />
      <CertPublisher Value="Dell Technologies Inc." />
    </Signer>
    <Signer Name="Allow CN = Dell Technologies Inc. issued by Entrust Code Signing CA - OVCS2" ID="ID_SIGNER_A_13">
      <CertRoot Type="TBS" Value="2893F2A6FDB108AC57D597754078350C55CAA720A072BD7BA170C8414B6749ECB2F875D29C77BC7AB7BF43D30D78424246F83CF66918BB601CE234429ACF3F2C" />
      <CertPublisher Value="Dell Technologies Inc." />
    </Signer>
  </Signers>
  <SigningScenarios>
    <SigningScenario ID="ID_SIGNINGSCENARIO_DRIVERS_1" FriendlyName="Auto generated policy on 09-24-2021" Value="131">
      <ProductSigners />
    </SigningScenario>
    <SigningScenario ID="ID_SIGNINGSCENARIO_WINDOWS" FriendlyName="Auto generated policy on 09-24-2021" Value="12">
      <ProductSigners>
        <AllowedSigners>
          <AllowedSigner SignerId="ID_SIGNER_A_4" />
          <AllowedSigner SignerId="ID_SIGNER_A_5" />
          <AllowedSigner SignerId="ID_SIGNER_A_6" />
          <AllowedSigner SignerId="ID_SIGNER_A_7" />
          <AllowedSigner SignerId="ID_SIGNER_A_8" />
          <AllowedSigner SignerId="ID_SIGNER_A_9" />
          <AllowedSigner SignerId="ID_SIGNER_A_10" />
          <AllowedSigner SignerId="ID_SIGNER_A_11" />
          <AllowedSigner SignerId="ID_SIGNER_A_12" />
          <AllowedSigner SignerId="ID_SIGNER_A_13" />
        </AllowedSigners>
      </ProductSigners>
    </SigningScenario>
  </SigningScenarios>
  <UpdatePolicySigners />
  <CiSigners>
    <CiSigner SignerId="ID_SIGNER_A_4" />
    <CiSigner SignerId="ID_SIGNER_A_5" />
    <CiSigner SignerId="ID_SIGNER_A_6" />
    <CiSigner SignerId="ID_SIGNER_A_7" />
    <CiSigner SignerId="ID_SIGNER_A_8" />
    <CiSigner SignerId="ID_SIGNER_A_9" />
    <CiSigner SignerId="ID_SIGNER_A_10" />
    <CiSigner SignerId="ID_SIGNER_A_11" />
    <CiSigner SignerId="ID_SIGNER_A_12" />
    <CiSigner SignerId="ID_SIGNER_A_13" />
  </CiSigners>
  <HvciOptions>0</HvciOptions>
  <Settings>
    <Setting Provider="PolicyInfo" Key="Information" ValueName="Name">
      <Value>
        <String>SupplementalTemplate</String>
      </Value>
    </Setting>
    <Setting Provider="PolicyInfo" Key="Information" ValueName="Id">
      <Value>
        <String>041922</String>
      </Value>
    </Setting>
  </Settings>
</SiPolicy>
